wfstructlog/__init__.py
wfstructlog/wfStructLog.py
wfstructlog-0.1.0.dist-info/LICENSE
wfstructlog-0.1.0.dist-info/METADATA
wfstructlog-0.1.0.dist-info/WHEEL
wfstructlog-0.1.0.dist-info/top_level.txt
wfstructlog-0.1.0.dist-info/RECORD
