Metadata-Version: 2.1
Name: wfstructlog
Version: 0.1.0
Summary: A structlog library for wildfire
Home-page: UNKNOWN
Author: Jie Shen
Author-email: jshen@paloaltonetworks.com
License: UNKNOWN
Platform: UNKNOWN
Classifier: Programming Language :: Python :: 3
Classifier: License :: OSI Approved :: MIT License
Classifier: Operating System :: OS Independent
License-File: LICENSE
Requires-Dist: structlog (==24.2.0)
Requires-Dist: orjson (==3.10.3)
